<?xml version="1.0" encoding="utf-8"?>
<Defs>
  <QuestEditor_Library.CustomMapDataDef>
    <defName>LoGiQ_Map_MilitaryBaseB</defName>
    <label>Enemy military base</label>
    <description>Military base, from where raiders attacking the colony.</description>
	<tags><li>LoGiQ_MilitaryBaseRoot</li></tags>
    <fogged>true</fogged>
    <size>(30, 1, 30)</size>
    <commonality>1</commonality>
	<faction>MapFaction</faction>
    <customThings>
      <li Class="QuestEditor_Library.CustomThingData_LootBox">
        <def>LoGiQ_Cabinet</def>
        <stuff>Plasteel</stuff>
        <position>(24,0,4)</position>
        <lootBoxName>BossCrate</lootBoxName>
        <tickToOpen>200</tickToOpen>
        <openReport>CQF_Open</openReport>
        <destroyAfterOpening>false</destroyAfterOpening>
        <lootDef>LoGiQ_LootBox_HQAttack_Boss</lootDef>
      </li>
      <li Class="QuestEditor_Library.CustomThingData_InteractableThing">
        <def>LoGiQ_InteractableConsole</def>
        <position>(21,0,2)</position>
      </li>
      <li Class="QuestEditor_Library.CustomThingData_LootBox">
        <def>LoGiQ_Cabinet</def>
        <stuff>Steel</stuff>
        <customDescription>Search for something usefull</customDescription>
        <position>(9,0,18)</position>
        <lootBoxName>ArmoryCrate</lootBoxName>
        <tickToOpen>150</tickToOpen>
        <openReport>CQF_Open</openReport>
        <destroyAfterOpening>false</destroyAfterOpening>
        <lootDef>LoGiQ_LootBox_HQAttack_Armory</lootDef>
      </li>
    </customThings>
    <pawns>
      <li>
        <key>(23, 0, 4)</key>
        <value>
          <li>
            <dataName>Boss</dataName>
            <kind>LoGiQ_GarrisonCommander</kind>
            <enableLord>true</enableLord>
            <count>1</count>
            <faction>MapFaction</faction>
            <duty>Defend</duty>
            <spawnType>MapGeneration</spawnType>
            <inventoryThings>
              <li Class="QuestEditor_Library.CQFThingDefCount">
                <count>3</count>
                <thing>Weapon_GrenadeFrag</thing>
              </li>
            </inventoryThings>
          </li>
          <li>
            <dataName>BossGuard</dataName>
            <kind>Mercenary_Elite</kind>
            <enableLord>true</enableLord>
            <count>2</count>
            <faction>MapFaction</faction>
            <duty>Defend</duty>
            <spawnType>MapGeneration</spawnType>
          </li>
        </value>
      </li>
      <li>
        <key>(25, 0, 18)</key>
        <value>
          <li>
            <dataName>TroopsR</dataName>
            <kind>Mercenary_Elite</kind>
            <enableLord>true</enableLord>
            <count>6</count>
            <faction>MapFaction</faction>
            <duty>Defend</duty>
            <spawnType>MapGeneration</spawnType>
          </li>
        </value>
      </li>
      <li>
        <key>(15, 0, 18)</key>
        <value>
          <li>
            <dataName>TroopsL</dataName>
            <kind>Mercenary_Heavy</kind>
            <enableLord>true</enableLord>
            <count>6</count>
            <faction>MapFaction</faction>
            <duty>Defend</duty>
            <spawnType>MapGeneration</spawnType>
          </li>
        </value>
      </li>
      <li>
        <key>(20, 0, 17)</key>
        <value>
          <li>
            <dataName>MortarTeam</dataName>
            <kind>LoGiQ_Mercenary_Crew</kind>
            <enableLord>true</enableLord>
            <count>3</count>
            <faction>MapFaction</faction>
            <duty>LoGiQ_ManClosestTurretCE</duty>
            <spawnType>MapGeneration</spawnType>
          </li>
        </value>
      </li>
      <li>
        <key>(2, 0, 23)</key>
        <value>
          <li>
            <dataName>TroopsEdge</dataName>
            <kind>Mercenary_Sniper</kind>
            <enableLord>true</enableLord>
            <count>2</count>
            <faction>MapFaction</faction>
            <duty>Defend</duty>
            <spawnType>MapGeneration</spawnType>
            <extraKinds>
              <li>Mercenary_Gunner</li>
              <li>Grenadier_Destructive</li>
            </extraKinds>
          </li>
        </value>
      </li>
    </pawns>
	<roofRects>
      <li>
        <key>RoofConstructed</key>
        <value>
          <li>(6,8,20,13)</li>
          <li>(6,14,17,22)</li>
          <li>(17,7,20,7)</li>
          <li>(19,1,26,5)</li>
          <li>(23,7,28,23)</li>
          <li>(12,23,17,23)</li>
        </value>
      </li>
    </roofRects>
    <terrainsRect>
      <li>
        <key>Gravel</key>
        <value>
          <li>(2,1,12,3)</li>
          <li>(2,4,8,6)</li>
          <li>(4,7,10,7)</li>
          <li>(4,8,5,23)</li>
          <li>(0,11,1,18)</li>
          <li>(13,2,19,3)</li>
          <li>(12,7,19,7)</li>
          <li>(13,6,16,6)</li>
          <li>(12,8,12,10)</li>
          <li>(12,12,12,23)</li>
          <li>(13,13,19,13)</li>
          <li>(19,0,29,1)</li>
          <li>(19,4,19,5)</li>
          <li>(20,5,21,5)</li>
          <li>(3,21,3,23)</li>
          <li>(1,22,2,24)</li>
          <li>(23,5,26,5)</li>
          <li>(6,23,10,23)</li>
          <li>(24,7,29,7)</li>
          <li>(26,2,29,3)</li>
          <li>(4,26,27,28)</li>
          <li>(26,4,26,4)</li>
          <li>(13,23,16,23)</li>
          <li>(24,13,29,13)</li>
          <li>(28,8,29,12)</li>
          <li>(28,14,29,23)</li>
          <li>(14,29,17,29)</li>
          <li>(24,23,27,23)</li>
          <li>(24,29,27,29)</li>
        </value>
      </li>
      <li>
        <key>PavedTile</key>
        <value>
          <li>(6,8,11,22)</li>
          <li>(13,8,19,12)</li>
          <li>(12,11,12,11)</li>
          <li>(13,14,16,22)</li>
          <li>(20,2,25,4)</li>
          <li>(22,5,22,5)</li>
          <li>(24,8,27,12)</li>
          <li>(24,14,27,22)</li>
        </value>
      </li>
      <li>
        <key>Concrete</key>
        <value>
          <li>(11,5,18,5)</li>
          <li>(11,6,12,6)</li>
          <li>(11,7,11,7)</li>
          <li>(17,6,29,6)</li>
          <li>(20,7,23,23)</li>
          <li>(17,14,19,24)</li>
          <li>(11,23,11,24)</li>
          <li>(12,24,16,24)</li>
          <li>(20,24,21,24)</li>
        </value>
      </li>
    </terrainsRect>
    <thingDatas>
      <li>
        <def>Sandbags</def>
        <stuff>Cloth</stuff>
        <allRect>
          <li>(2,3,3,3)</li>
          <li>(2,4,2,6)</li>
          <li>(3,6,3,6)</li>
          <li>(9,1,12,1)</li>
          <li>(10,2,11,2)</li>
          <li>(20,0,25,0)</li>
          <li>(1,22,2,22)</li>
          <li>(1,23,1,24)</li>
          <li>(2,24,2,24)</li>
          <li>(4,27,4,28)</li>
          <li>(7,27,7,28)</li>
          <li>(11,26,12,27)</li>
          <li>(5,28,6,28)</li>
          <li>(10,27,10,27)</li>
          <li>(13,27,14,28)</li>
          <li>(29,8,29,22)</li>
          <li>(17,27,21,27)</li>
          <li>(19,26,20,26)</li>
          <li>(14,29,17,29)</li>
          <li>(17,28,18,28)</li>
          <li>(24,27,24,29)</li>
          <li>(27,27,27,29)</li>
          <li>(25,29,26,29)</li>
        </allRect>
      </li>
      <li>
        <def>LoGiQ_REPL_2x2_Auto_Flack</def>
        <position>(25,0,27)</position>
      </li>
      <li>
        <def>LoGiQ_REPL_1x1_Auto_LMG</def>
        <allRect>
          <li>(5,27,6,27)</li>
        </allRect>
      </li>
      <li>
        <def>Barricade</def>
        <stuff>BlocksSandstone</stuff>
        <allRect>
          <li>(4,9,4,12)</li>
          <li>(1,11,1,12)</li>
          <li>(0,12,0,16)</li>
          <li>(4,14,4,16)</li>
          <li>(1,16,1,17)</li>
          <li>(4,18,4,21)</li>
          <li>(26,0,29,0)</li>
          <li>(29,1,29,3)</li>
        </allRect>
      </li>
      <li>
        <def>LoGiQ_REPL_2x2_Auto_Flack</def>
        <rotation>1</rotation>
        <position>(27,0,2)</position>
      </li>
      <li>
        <def>Wall</def>
        <stuff>BlocksSandstone</stuff>
        <allRect>
          <li>(6,8,10,8)</li>
          <li>(6,9,6,10)</li>
          <li>(6,12,6,14)</li>
          <li>(7,13,10,13)</li>
          <li>(6,16,6,18)</li>
          <li>(12,13,17,13)</li>
          <li>(7,17,10,17)</li>
          <li>(12,14,12,23)</li>
          <li>(19,1,26,1)</li>
          <li>(19,2,19,5)</li>
          <li>(20,5,21,5)</li>
          <li>(6,20,6,22)</li>
          <li>(17,14,17,14)</li>
          <li>(7,22,10,22)</li>
          <li>(17,16,17,20)</li>
          <li>(23,5,26,5)</li>
          <li>(23,7,28,7)</li>
          <li>(23,8,23,9)</li>
          <li>(23,11,23,14)</li>
          <li>(26,2,26,4)</li>
          <li>(13,23,18,23)</li>
          <li>(24,13,28,13)</li>
          <li>(17,22,17,22)</li>
          <li>(23,16,23,20)</li>
          <li>(28,8,28,12)</li>
          <li>(28,14,28,23)</li>
          <li>(22,23,27,23)</li>
          <li>(23,22,23,22)</li>
        </allRect>
      </li>
      <li>
        <def>ChemfuelPoweredGenerator</def>
        <storedEnergy>30</storedEnergy>
        <allRect>
          <li>(24,11,24,11)</li>
          <li>(26,11,26,11)</li>
        </allRect>
      </li>
      <li>
        <def>Battery</def>
        <storedEnergy>600</storedEnergy>
        <allRect>
          <li>(24,8,26,8)</li>
        </allRect>
      </li>
      <li>
        <def>ShelfSmall</def>
        <stuff>Steel</stuff>
        <position>(27,0,8)</position>
      </li>
      <li>
        <def>Door</def>
        <stuff>WoodLog</stuff>
        <rotation>1</rotation>
        <allRect>
          <li>(12,11,12,11)</li>
          <li>(20,10,20,10)</li>
          <li>(17,15,17,15)</li>
          <li>(17,21,17,21)</li>
          <li>(23,15,23,15)</li>
          <li>(23,21,23,21)</li>
        </allRect>
      </li>
      <li>
        <def>Door</def>
        <stuff>Steel</stuff>
        <rotation>1</rotation>
        <allRect>
          <li>(6,11,6,11)</li>
          <li>(6,15,6,15)</li>
          <li>(6,19,6,19)</li>
          <li>(23,10,23,10)</li>
        </allRect>
      </li>
      <li>
        <def>Wall</def>
        <stuff>WoodLog</stuff>
        <allRect>
          <li>(5,2,9,2)</li>
          <li>(12,2,16,2)</li>
          <li>(12,7,20,7)</li>
          <li>(13,6,16,6)</li>
          <li>(12,8,12,10)</li>
          <li>(12,12,12,12)</li>
          <li>(20,8,20,9)</li>
          <li>(18,13,20,13)</li>
          <li>(20,11,20,12)</li>
          <li>(4,26,7,26)</li>
          <li>(9,26,10,26)</li>
          <li>(13,26,18,26)</li>
          <li>(21,26,22,26)</li>
        </allRect>
      </li>
      <li>
        <def>LoGiQ_REPL_2x2_Man_Mortar</def>
        <allRect>
          <li>(18,19,18,19)</li>
          <li>(21,19,21,19)</li>
        </allRect>
      </li>
      <li>
        <def>ShelfSmall</def>
        <stuff>Steel</stuff>
        <rotation>3</rotation>
        <allRect>
          <li>(22,16,22,17)</li>
        </allRect>
      </li>
      <li>
        <def>ShelfSmall</def>
        <stuff>Steel</stuff>
        <rotation>1</rotation>
        <position>(18,0,17)</position>
      </li>
      <li>
        <def>LoGiQ_REPL_2x2_Man_Mortar_ammo</def>
        <count>20</count>
        <allRect>
          <li>(18,17,18,17)</li>
          <li>(22,17,22,17)</li>
        </allRect>
      </li>
      <li>
        <def>Bed</def>
        <stuff>Steel</stuff>
        <rotation>3</rotation>
        <allRect>
          <li>(25,3,25,3)</li>
          <li>(27,14,27,14)</li>
          <li>(27,16,27,16)</li>
          <li>(27,18,27,18)</li>
          <li>(27,20,27,20)</li>
          <li>(27,22,27,22)</li>
        </allRect>
      </li>
      <li>
        <def>EndTable</def>
        <stuff>WoodLog</stuff>
        <rotation>2</rotation>
        <position>(25,0,2)</position>
      </li>
      <li>
        <def>Door</def>
        <stuff>Steel</stuff>
        <allRect>
          <li>(11,8,11,8)</li>
          <li>(11,13,11,13)</li>
          <li>(11,17,11,17)</li>
          <li>(22,5,22,5)</li>
          <li>(11,22,11,22)</li>
        </allRect>
      </li>
      <li>
        <def>LoGiQ_REPL_1x1_Auto_LMG</def>
        <rotation>3</rotation>
        <allRect>
          <li>(1,13,1,15)</li>
        </allRect>
      </li>
      <li>
        <def>HiddenConduit</def>
        <allRect>
          <li>(1,13,28,13)</li>
          <li>(12,14,12,26)</li>
          <li>(23,5,26,5)</li>
          <li>(23,6,23,12)</li>
          <li>(26,1,26,4)</li>
          <li>(5,26,7,26)</li>
          <li>(23,14,23,25)</li>
          <li>(10,26,11,26)</li>
          <li>(13,26,22,26)</li>
          <li>(24,26,25,26)</li>
        </allRect>
      </li>
      <li>
        <def>Bed</def>
        <stuff>Steel</stuff>
        <rotation>1</rotation>
        <allRect>
          <li>(13,14,13,14)</li>
          <li>(13,16,13,16)</li>
          <li>(13,18,13,18)</li>
          <li>(13,20,13,20)</li>
          <li>(13,22,13,22)</li>
        </allRect>
      </li>
      <li>
        <def>Table1x2c</def>
        <stuff>WoodLog</stuff>
        <rotation>1</rotation>
        <allRect>
          <li>(14,10,14,10)</li>
          <li>(16,10,16,10)</li>
        </allRect>
      </li>
      <li>
        <def>TubeTelevision</def>
        <rotation>2</rotation>
        <position>(16,0,12)</position>
      </li>
      <li>
        <def>DiningChair</def>
        <stuff>Steel</stuff>
        <rotation>2</rotation>
        <allRect>
          <li>(8,10,8,10)</li>
          <li>(14,11,17,11)</li>
          <li>(21,4,21,4)</li>
        </allRect>
      </li>
      <li>
        <def>DiningChair</def>
        <stuff>Steel</stuff>
        <allRect>
          <li>(14,9,17,9)</li>
        </allRect>
      </li>
      <li>
        <def>ShelfSmall</def>
        <stuff>WoodLog</stuff>
        <rotation>2</rotation>
        <position>(13,0,12)</position>
      </li>
      <li>
        <def>ShelfSmall</def>
        <stuff>WoodLog</stuff>
        <position>(13,0,8)</position>
      </li>
      <li>
        <def>DiningChair</def>
        <stuff>Steel</stuff>
        <rotation>3</rotation>
        <position>(18,0,10)</position>
      </li>
      <li>
        <def>WallLamp</def>
        <position>(17,0,12)</position>
      </li>
      <li>
        <def>WallLamp</def>
        <rotation>3</rotation>
        <allRect>
          <li>(13,15,13,15)</li>
          <li>(13,21,13,21)</li>
        </allRect>
      </li>
      <li>
        <def>WallLamp</def>
        <rotation>1</rotation>
        <allRect>
          <li>(27,15,27,15)</li>
          <li>(27,21,27,21)</li>
        </allRect>
      </li>
      <li>
        <def>Heater</def>
        <allRect>
          <li>(16,22,16,22)</li>
          <li>(24,22,24,22)</li>
        </allRect>
      </li>
      <li>
        <def>PassiveCooler</def>
        <storedEnergy>50</storedEnergy>
        <allRect>
          <li>(16,14,16,14)</li>
          <li>(24,14,24,14)</li>
        </allRect>
      </li>
      <li>
        <def>Shelf</def>
        <stuff>Steel</stuff>
        <rotation>1</rotation>
        <allRect>
          <li>(24,17,24,17)</li>
          <li>(24,20,24,20)</li>
        </allRect>
      </li>
      <li>
        <def>Shelf</def>
        <stuff>Steel</stuff>
        <rotation>3</rotation>
        <allRect>
          <li>(7,20,10,20)</li>
          <li>(16,16,16,16)</li>
          <li>(16,19,16,19)</li>
        </allRect>
      </li>
      <li>
        <def>FueledStove</def>
        <rotation>2</rotation>
        <storedEnergy>50</storedEnergy>
        <position>(8,0,9)</position>
      </li>
      <li>
        <def>Shelf</def>
        <stuff>WoodLog</stuff>
        <rotation>2</rotation>
        <allRect>
          <li>(8,12,8,12)</li>
          <li>(10,12,10,12)</li>
        </allRect>
      </li>
      <li>
        <def>Shelf</def>
        <stuff>WoodLog</stuff>
        <rotation>3</rotation>
        <position>(10,0,9)</position>
      </li>
      <li>
        <def>Shelf</def>
        <stuff>Steel</stuff>
        <rotation>2</rotation>
        <allRect>
          <li>(8,16,8,16)</li>
          <li>(10,16,10,16)</li>
        </allRect>
      </li>
      <li>
        <def>Shelf</def>
        <stuff>Steel</stuff>
        <allRect>
          <li>(7,14,7,14)</li>
          <li>(9,14,9,14)</li>
          <li>(7,18,7,18)</li>
        </allRect>
      </li>
      <li>
        <def>LoGiQ_REPL_2x2_Auto_AT</def>
        <position>(15,0,27)</position>
      </li>
      <li>
        <def>WoodLog</def>
        <count>75</count>
        <allRect>
          <li>(7,14,7,14)</li>
          <li>(7,16,7,16)</li>
        </allRect>
      </li>
      <li>
        <def>MealSurvivalPack</def>
        <count>10</count>
        <allRect>
          <li>(7,12,10,12)</li>
          <li>(13,8,13,8)</li>
          <li>(13,12,13,12)</li>
        </allRect>
      </li>
      <li>
        <def>RawPotatoes</def>
        <count>75</count>
        <allRect>
          <li>(10,9,10,10)</li>
          <li>(10,9,10,10)</li>
          <li>(10,9,10,10)</li>
        </allRect>
      </li>
      <li>
        <def>Steel</def>
        <count>75</count>
        <allRect>
          <li>(8,14,9,14)</li>
          <li>(8,14,9,14)</li>
          <li>(8,16,9,16)</li>
          <li>(8,16,9,16)</li>
        </allRect>
      </li>
      <li>
        <def>Plasteel</def>
        <count>75</count>
        <allRect>
          <li>(10,16,10,16)</li>
          <li>(10,16,10,16)</li>
        </allRect>
      </li>
      <li>
        <def>Chemfuel</def>
        <count>150</count>
        <allRect>
          <li>(27,8,27,8)</li>
          <li>(27,8,27,8)</li>
        </allRect>
      </li>
      <li>
        <def>MedicineIndustrial</def>
        <count>12</count>
        <position>(10,0,14)</position>
      </li>
      <li>
        <def>Gun_HeavySMG</def>
        <quality>Excellent</quality>
        <allRect>
          <li>(7,21,10,21)</li>
        </allRect>
      </li>
      <li>
        <def>Apparel_FlakJacket</def>
        <quality>Good</quality>
        <color>RGBA(0.620, 0.620, 0.620, 1.000)</color>
        <allRect>
          <li>(7,18,8,18)</li>
        </allRect>
      </li>
      <li>
        <def>Apparel_SimpleHelmet</def>
        <stuff>Plasteel</stuff>
        <position>(7,0,20)</position>
      </li>
      <li>
        <def>Apparel_SimpleHelmet</def>
        <stuff>Plasteel</stuff>
        <quality>Excellent</quality>
        <allRect>
          <li>(8,20,8,20)</li>
          <li>(8,20,8,20)</li>
        </allRect>
      </li>
      <li>
        <def>Apparel_SimpleHelmet</def>
        <stuff>Steel</stuff>
        <quality>Good</quality>
        <allRect>
          <li>(7,20,7,20)</li>
          <li>(7,20,7,20)</li>
        </allRect>
      </li>
      <li>
        <def>Apparel_SimpleHelmet</def>
        <stuff>Steel</stuff>
        <position>(8,0,20)</position>
      </li>
      <li>
        <def>Apparel_FlakPants</def>
        <quality>Good</quality>
        <position>(9,0,20)</position>
      </li>
      <li>
        <def>Apparel_FlakPants</def>
        <position>(9,0,20)</position>
      </li>
      <li>
        <def>Apparel_FlakVest</def>
        <quality>Good</quality>
        <color>RGBA(0.330, 0.330, 0.330, 1.000)</color>
        <position>(10,0,20)</position>
      </li>
      <li>
        <def>Apparel_FlakVest</def>
        <color>RGBA(0.650, 0.650, 0.650, 1.000)</color>
        <position>(10,0,20)</position>
      </li>
      <li>
        <def>TrapSpike</def>
        <stuff>Steel</stuff>
        <allRect>
          <li>(17,2,17,2)</li>
          <li>(7,23,7,23)</li>
          <li>(9,23,9,23)</li>
        </allRect>
      </li>
      <li>
        <def>Barricade</def>
        <stuff>Steel</stuff>
        <allRect>
          <li>(6,4,6,4)</li>
          <li>(6,6,6,6)</li>
          <li>(8,4,8,4)</li>
          <li>(8,6,8,6)</li>
        </allRect>
      </li>
      <li>
        <def>LoGiQ_REPL_2x2_Man_Mortar</def>
        <rotation>2</rotation>
        <position>(20,0,15)</position>
      </li>
      <li>
        <def>Shell_Incendiary</def>
        <count>20</count>
        <position>(22,0,16)</position>
      </li>
    </thingDatas>
    <customSteps>
      <li Class="QuestEditor_Library.CustomMapStep_MapPart">
        <count>4~5</count>
        <set>
          <tags>
            <LoGiQ_MilitaryBasePostL>1</LoGiQ_MilitaryBasePostL>
          </tags>
        </set>
      </li>
      <li Class="LoGiQ.GenStep_Replacement">
         <replaceDataDefNames>
			<li>LoGiQ_REPL_1x1_Auto_LMG</li> 
			<li>LoGiQ_REPL_2x2_Auto_AT</li>
			<li>LoGiQ_REPL_2x2_Auto_Flack</li>
			<li>LoGiQ_REPL_2x2_Man_Mortar</li>
		</replaceDataDefNames>
	  </li>
    </customSteps>
  </QuestEditor_Library.CustomMapDataDef>
</Defs>